not_my_board-0.12.0.dist-info/METADATA
not_my_board-0.12.0.dist-info/WHEEL
not_my_board-0.12.0.dist-info/entry_points.txt
not_my_board-0.12.0.dist-info/LICENSE.txt
not_my_board/__init__.py
not_my_board/__main__.py
not_my_board/_agent.py
not_my_board/_client.py
not_my_board/_export.py
not_my_board/_http.py
not_my_board/_models.py
not_my_board/_hub.py
not_my_board/_usbip.py
not_my_board/_util/__init__.py
not_my_board/_util/_asyncio.py
not_my_board/_util/_logging.py
not_my_board/_util/_matching.py
not_my_board/_util/_parser.py
not_my_board/_util/_flat_format.py
not_my_board/_jsonrpc/__init__.py
not_my_board/_jsonrpc/_protocol.py
not_my_board/_jsonrpc/_websocket.py
not_my_board/_auth/__init__.py
not_my_board/_auth/_openid.py
not_my_board/_auth/_login.py
not_my_board/cli/__init__.py
not_my_board/__about__.py
not_my_board-0.12.0.dist-info/RECORD
