Metadata-Version: 2.1
Name: not-my-board
Version: 0.12.0
Summary: Tool to setup, manage and use a board farm 
Keywords: board-farm,embedded,testing
Author-Email: Simon Holesch <simon@holesch.de>
License: MIT License
Classifier: Development Status :: 4 - Beta
Classifier: Environment :: Console
Classifier: Intended Audience :: Developers
Classifier: License :: OSI Approved :: MIT License
Classifier: Operating System :: POSIX :: Linux
Classifier: Programming Language :: Python
Classifier: Programming Language :: Python :: 3.10
Classifier: Programming Language :: Python :: 3.11
Classifier: Programming Language :: Python :: 3.12
Classifier: Programming Language :: Python :: 3.13
Classifier: Programming Language :: Python :: 3.14
Classifier: Topic :: Software Development :: Embedded Systems
Classifier: Topic :: Software Development :: Testing
Project-URL: Documentation, http://not-my-board.readthedocs.io
Project-URL: Issues, https://github.com/holesch/not-my-board/issues
Project-URL: Source, https://github.com/holesch/not-my-board
Requires-Python: >=3.10
Requires-Dist: asgineer
Requires-Dist: async-timeout~=5.0; python_version < "3.11"
Requires-Dist: colorlog
Requires-Dist: h11
Requires-Dist: pyjwt[crypto]
Requires-Dist: tabulate
Requires-Dist: tomli; python_version < "3.11"
Requires-Dist: uvicorn
Requires-Dist: websockets
Provides-Extra: test
Requires-Dist: black; extra == "test"
Requires-Dist: codespell; extra == "test"
Requires-Dist: isort; extra == "test"
Requires-Dist: mypy; extra == "test"
Requires-Dist: pytest; extra == "test"
Requires-Dist: pytest-asyncio~=0.21.2; extra == "test"
Requires-Dist: pytest-cov; extra == "test"
Requires-Dist: ruff; extra == "test"
Provides-Extra: docs
Requires-Dist: furo; extra == "docs"
Requires-Dist: myst-parser; extra == "docs"
Requires-Dist: sphinx; extra == "docs"
Requires-Dist: sphinx-copybutton; extra == "docs"
Requires-Dist: sphinxext-opengraph; extra == "docs"
